401N/VCBmCLED/VCBmCLED.v
`ifndef m
	`define m 4
`endif
module VCBmCLED(input ce,          output reg [`m-1:0] Q = 0,
                input up,          output wire CEO,
                input [`m-1:0] di, output wire TC,
                input L,
                input clk,
                input clr);
	assign TC  = up ? (Q == (1<<`m)-1) : (Q == 0);
	assign CEO = ce & TC;
	always @(posedge clk) begin
		if (clr) Q <= 0;
		else     Q <= L ? di : (up & ce ? Q+1 : (!up &ce ? Q-1 : Q));
	end
endmodule

401N/VCBmCLED/VCBmCLED_tb.v
module VCBmCLED_test;
	reg ce;
	reg clk;
	reg clr;

	wire [3:0] Q;
	wire [3:0] DI = 4'b0110;
	wire TC;
	wire CEO;

	reg L  = 1'b1;
	reg up = 1'b1;

	VCBmCLED uut(.ce(ce),   .Q(Q),
						  .up(up), .TC(TC),
					    .di(DI), .CEO(CEO),
						  .L(L),
						  .clk(clk),
						  .clr(clr));
	
	// sync signal generator
	parameter Tclk = 20; // period sync sig = 20 ns
	always begin
		clk = 1;
		#(Tclk/2);
		clk = 0;
		#(Tclk/2);
	end

	// periodic ce sig generator
	parameter Tce = 40; // period ce sig = 160 ns
	always begin
		ce = 0;
		#(Tce/2);
		ce = 1;
		#(Tce/2);
	end
	initial begin
		$dumpfile("VCBmCLED.vcd");
    $dumpvars(0, VCBmCLED_test);
		clr = 0;
		#20;   L = 1'b0;
		#380;  clr = 1; L = 1'b1;
		#40;   clr = 0;
		#40;   up = 1'b0; L = 1'b0;
		#811;  clr = 1;
		#270;  clr = 0;
		$finish();
	end
endmodule

401N/VCBmCLED/VCBmCLED.vcd
$date
	Thu Sep 14 04:37:49 2023
$end
$version
	Icarus Verilog
$end
$timescale
	1s
$end
$scope module VCBmCLED_test $end
$var wire 4 ! DI [3:0] $end
$var wire 1 " TC $end
$var wire 4 # Q [3:0] $end
$var wire 1 $ CEO $end
$var parameter 32 % Tce $end
$var parameter 32 & Tclk $end
$var reg 1 ' L $end
$var reg 1 ( ce $end
$var reg 1 ) clk $end
$var reg 1 * clr $end
$var reg 1 + up $end
$scope module uut $end
$var wire 1 $ CEO $end
$var wire 1 ' L $end
$var wire 1 ( ce $end
$var wire 1 ) clk $end
$var wire 1 * clr $end
$var wire 4 , di [3:0] $end
$var wire 1 + up $end
$var wire 1 " TC $end
$var reg 4 - Q [3:0] $end
$upscope $end
$upscope $end
$enddefinitions $end
$comment Show the parameter values. $end
$dumpall
b10100 &
b101000 %
$end
#0
$dumpvars
b110 -
b110 ,
1+
0*
1)
0(
1'
0$
b110 #
0"
b110 !
$end
#10
0)
#20
b111 #
b111 -
1)
0'
1(
#30
0)
#40
1)
0(
#50
0)
#60
b1000 #
b1000 -
1)
1(
#70
0)
#80
1)
0(
#90
0)
#100
b1001 #
b1001 -
1)
1(
#110
0)
#120
1)
0(
#130
0)
#140
b1010 #
b1010 -
1)
1(
#150
0)
#160
1)
0(
#170
0)
#180
b1011 #
b1011 -
1)
1(
#190
0)
#200
1)
0(
#210
0)
#220
b1100 #
b1100 -
1)
1(
#230
0)
#240
1)
0(
#250
0)
#260
b1101 #
b1101 -
1)
1(
#270
0)
#280
1)
0(
#290
0)
#300
b1110 #
b1110 -
1)
1(
#310
0)
#320
1)
0(
#330
0)
#340
1$
1"
b1111 #
b1111 -
1)
1(
#350
0)
#360
0$
1)
0(
#370
0)
#380
0"
b0 #
b0 -
0$
1)
1(
#390
0)
#400
1)
0(
1'
1*
#410
0)
#420
1)
1(
#430
0)
#440
b110 #
b110 -
1)
0(
0*
#450
0)
#460
1)
1(
#470
0)
#480
1)
0(
0'
0+
#490
0)
#500
b101 #
b101 -
1)
1(
#510
0)
#520
1)
0(
#530
0)
#540
b100 #
b100 -
1)
1(
#550
0)
#560
1)
0(
#570
0)
#580
b11 #
b11 -
1)
1(
#590
0)
#600
1)
0(
#610
0)
#620
b10 #
b10 -
1)
1(
#630
0)
#640
1)
0(
#650
0)
#660
b1 #
b1 -
1)
1(
#670
0)
#680
1)
0(
#690
0)
#700
1$
1"
b0 #
b0 -
1)
1(
#710
0)
#720
0$
1)
0(
#730
0)
#740
0"
b1111 #
b1111 -
0$
1)
1(
#750
0)
#760
1)
0(
#770
0)
#780
b1110 #
b1110 -
1)
1(
#790
0)
#800
1)
0(
#810
0)
#820
b1101 #
b1101 -
1)
1(
#830
0)
#840
1)
0(
#850
0)
#860
b1100 #
b1100 -
1)
1(
#870
0)
#880
1)
0(
#890
0)
#900
b1011 #
b1011 -
1)
1(
#910
0)
#920
1)
0(
#930
0)
#940
b1010 #
b1010 -
1)
1(
#950
0)
#960
1)
0(
#970
0)
#980
b1001 #
b1001 -
1)
1(
#990
0)
#1000
1)
0(
#1010
0)
#1020
b1000 #
b1000 -
1)
1(
#1030
0)
#1040
1)
0(
#1050
0)
#1060
b111 #
b111 -
1)
1(
#1070
0)
#1080
1)
0(
#1090
0)
#1100
b110 #
b110 -
1)
1(
#1110
0)
#1120
1)
0(
#1130
0)
#1140
b101 #
b101 -
1)
1(
#1150
0)
#1160
1)
0(
#1170
0)
#1180
b100 #
b100 -
1)
1(
#1190
0)
#1200
1)
0(
#1210
0)
#1220
b11 #
b11 -
1)
1(
#1230
0)
#1240
1)
0(
#1250
0)
#1260
b10 #
b10 -
1)
1(
#1270
0)
#1280
1)
0(
#1290
0)
#1291
1*
#1300
1$
1"
b0 #
b0 -
1)
1(
#1310
0)
#1320
0$
1)
0(
#1330
0)
#1340
1$
1)
1(
#1350
0)
#1360
0$
1)
0(
#1370
0)
#1380
1$
1)
1(
#1390
0)
#1400
0$
1)
0(
#1410
0)
#1420
1$
1)
1(
#1430
0)
#1440
0$
1)
0(
#1450
0)
#1460
1$
1)
1(
#1470
0)
#1480
0$
1)
0(
#1490
0)
#1500
1$
1)
1(
#1510
0)
#1520
0$
1)
0(
#1530
0)
#1540
1$
1)
1(
#1550
0)
#1560
0$
1)
0(
#1561
0*
