401N/VCJ4RE/VCJ4RE.v
module VCJ4RE0(input ce,  output reg[3:0] Q = 0,
               input clk, output wire TC,
						   input clr, output wire CEO);
	assign TC  = (Q == 15);
	assign CEO = ce & TC;
	always @(posedge clk) begin
		Q <= clr ? 0 : (ce ? Q << 1 | !Q[3]: Q);
	end
endmodule

module VCJ4RE2(input ce,  output reg[3:0] Q = 2,
               input clk, output wire TC,
						   input clr, output wire CEO);
	assign TC  = (Q == 15);
	assign CEO = ce & TC;
	always @(posedge clk) begin
		Q <= clr ? 2 : (ce ? Q << 1 | !Q[3]: Q);
	end
endmodule

401N/VCJ4RE/VCJ4RE_tb.v
module VCJ4RE_test;
	reg ce;
	reg clk;
	reg clr;

	wire [3:0] Q0; wire [3:0] Q2;
	wire TC0;      wire TC2;
	wire CEO0;     wire CEO2;

	VCJ4RE0 uut0(.ce(ce),   .Q(Q0),
						   .clk(clk), .TC(TC0),
					     .clr(clr), .CEO(CEO0));

	VCJ4RE2 uut2(.ce(ce),   .Q(Q2),
	             .clk(clk), .TC(TC2),
						   .clr(clr), .CEO(CEO2));
	// sync signal generator
	parameter Tclk = 20; // period sync sig = 20 ns
	always begin
		clk = 1;
		#(Tclk/2);
		clk = 0;
		#(Tclk/2);
	end

	// periodic ce sig generator
	parameter Tce = 40; // period ce sig = 160 ns
	always begin
		ce = 0;
		#(Tce/2);
		ce = 1;
		#(Tce/2);
	end

	initial begin
		$dumpfile("VCJ4RE.vcd");
    $dumpvars(0, VCJ4RE_test);
		clr = 0;
		#380;  clr = 1;
		#10;   clr = 0;
		#811;  clr = 1;
		#270;  clr = 0;
		$finish();
	end
endmodule

401N/VCJ4RE/VCJ4RE.vcd
$date
	Thu Sep 14 04:37:49 2023
$end
$version
	Icarus Verilog
$end
$timescale
	1s
$end
$scope module VCJ4RE_test $end
$var wire 1 ! TC2 $end
$var wire 1 " TC0 $end
$var wire 4 # Q2 [3:0] $end
$var wire 4 $ Q0 [3:0] $end
$var wire 1 % CEO2 $end
$var wire 1 & CEO0 $end
$var parameter 32 ' Tce $end
$var parameter 32 ( Tclk $end
$var reg 1 ) ce $end
$var reg 1 * clk $end
$var reg 1 + clr $end
$scope module uut0 $end
$var wire 1 & CEO $end
$var wire 1 ) ce $end
$var wire 1 * clk $end
$var wire 1 + clr $end
$var wire 1 " TC $end
$var reg 4 , Q [3:0] $end
$upscope $end
$scope module uut2 $end
$var wire 1 % CEO $end
$var wire 1 ) ce $end
$var wire 1 * clk $end
$var wire 1 + clr $end
$var wire 1 ! TC $end
$var reg 4 - Q [3:0] $end
$upscope $end
$upscope $end
$enddefinitions $end
$comment Show the parameter values. $end
$dumpall
b10100 (
b101000 '
$end
#0
$dumpvars
b10 -
b0 ,
0+
1*
0)
0&
0%
b0 $
b10 #
0"
0!
$end
#10
0*
#20
b101 #
b101 -
b1 $
b1 ,
1*
1)
#30
0*
#40
1*
0)
#50
0*
#60
b1011 #
b1011 -
b11 $
b11 ,
1*
1)
#70
0*
#80
1*
0)
#90
0*
#100
b110 #
b110 -
b111 $
b111 ,
1*
1)
#110
0*
#120
1*
0)
#130
0*
#140
1&
b1101 #
b1101 -
1"
b1111 $
b1111 ,
1*
1)
#150
0*
#160
0&
1*
0)
#170
0*
#180
b1010 #
b1010 -
0"
b1110 $
b1110 ,
0&
1*
1)
#190
0*
#200
1*
0)
#210
0*
#220
b100 #
b100 -
b1100 $
b1100 ,
1*
1)
#230
0*
#240
1*
0)
#250
0*
#260
b1001 #
b1001 -
b1000 $
b1000 ,
1*
1)
#270
0*
#280
1*
0)
#290
0*
#300
b10 #
b10 -
b0 $
b0 ,
1*
1)
#310
0*
#320
1*
0)
#330
0*
#340
b101 #
b101 -
b1 $
b1 ,
1*
1)
#350
0*
#360
1*
0)
#370
0*
#380
b10 #
b10 -
b0 $
b0 ,
1*
1)
1+
#390
0*
0+
#400
1*
0)
#410
0*
#420
b101 #
b101 -
b1 $
b1 ,
1*
1)
#430
0*
#440
1*
0)
#450
0*
#460
b1011 #
b1011 -
b11 $
b11 ,
1*
1)
#470
0*
#480
1*
0)
#490
0*
#500
b110 #
b110 -
b111 $
b111 ,
1*
1)
#510
0*
#520
1*
0)
#530
0*
#540
1&
b1101 #
b1101 -
1"
b1111 $
b1111 ,
1*
1)
#550
0*
#560
0&
1*
0)
#570
0*
#580
b1010 #
b1010 -
0"
b1110 $
b1110 ,
0&
1*
1)
#590
0*
#600
1*
0)
#610
0*
#620
b100 #
b100 -
b1100 $
b1100 ,
1*
1)
#630
0*
#640
1*
0)
#650
0*
#660
b1001 #
b1001 -
b1000 $
b1000 ,
1*
1)
#670
0*
#680
1*
0)
#690
0*
#700
b10 #
b10 -
b0 $
b0 ,
1*
1)
#710
0*
#720
1*
0)
#730
0*
#740
b101 #
b101 -
b1 $
b1 ,
1*
1)
#750
0*
#760
1*
0)
#770
0*
#780
b1011 #
b1011 -
b11 $
b11 ,
1*
1)
#790
0*
#800
1*
0)
#810
0*
#820
b110 #
b110 -
b111 $
b111 ,
1*
1)
#830
0*
#840
1*
0)
#850
0*
#860
1&
b1101 #
b1101 -
1"
b1111 $
b1111 ,
1*
1)
#870
0*
#880
0&
1*
0)
#890
0*
#900
b1010 #
b1010 -
0"
b1110 $
b1110 ,
0&
1*
1)
#910
0*
#920
1*
0)
#930
0*
#940
b100 #
b100 -
b1100 $
b1100 ,
1*
1)
#950
0*
#960
1*
0)
#970
0*
#980
b1001 #
b1001 -
b1000 $
b1000 ,
1*
1)
#990
0*
#1000
1*
0)
#1010
0*
#1020
b10 #
b10 -
b0 $
b0 ,
1*
1)
#1030
0*
#1040
1*
0)
#1050
0*
#1060
b101 #
b101 -
b1 $
b1 ,
1*
1)
#1070
0*
#1080
1*
0)
#1090
0*
#1100
b1011 #
b1011 -
b11 $
b11 ,
1*
1)
#1110
0*
#1120
1*
0)
#1130
0*
#1140
b110 #
b110 -
b111 $
b111 ,
1*
1)
#1150
0*
#1160
1*
0)
#1170
0*
#1180
1&
b1101 #
b1101 -
1"
b1111 $
b1111 ,
1*
1)
#1190
0*
#1200
0&
1*
0)
#1201
1+
#1210
0*
#1220
b10 #
b10 -
0"
b0 $
b0 ,
0&
1*
1)
#1230
0*
#1240
1*
0)
#1250
0*
#1260
1*
1)
#1270
0*
#1280
1*
0)
#1290
0*
#1300
1*
1)
#1310
0*
#1320
1*
0)
#1330
0*
#1340
1*
1)
#1350
0*
#1360
1*
0)
#1370
0*
#1380
1*
1)
#1390
0*
#1400
1*
0)
#1410
0*
#1420
1*
1)
#1430
0*
#1440
1*
0)
#1450
0*
#1460
1*
1)
#1470
0*
#1471
0+
